abg_python/Untitled.ipynb
abg_python/__init__.py
abg_python/array_utils.py
abg_python/color_utils.py
abg_python/constants.py
abg_python/cosmo_utils.py
abg_python/directory_sankey.py
abg_python/distinct_colours.py
abg_python/fitting_utils.py
abg_python/function_utils.py
abg_python/math_utils.py
abg_python/pfh_colormaps.py
abg_python/physics_utils.py
abg_python/plot_utils.py
abg_python/selection_utils.py
abg_python/smooth_utils.py
abg_python/snapshot_utils.py
abg_python/system_utils.py
abg_python/data/filter_parameters.txt
abg_python/data/solar_magnitudes.txt
abg_python/galaxy/__init__.py
abg_python/galaxy/cosmoExtractor.py
abg_python/galaxy/firefly_utils.py
abg_python/galaxy/gal_utils.py
abg_python/galaxy/metadata_utils.py
abg_python/galaxy/movie_utils.py
abg_python/galaxy/scale_height_utils.py
abg_python/galaxy/sfr_utils.py
abg_python/interpolate/__init__.py
abg_python/interpolate/time_interpolate_utils.py
abg_python/parallel/__init__.py
abg_python/parallel/multiproc_utils.py
abg_python/parallel/multiprocessing_example.py
abg_python/parallel/parallel_hdf5_instructions.txt
abg_python/parallel/parallel_read.py
abg_python/parallel/test.sh
abg_python/tests/__init__.py
abg_python/tests/test_array_utils.py
abg_python/tests/test_function_utils.py
abg_python/tests/test_math_utils.py
abg_python/tests/test_selection_utils.py
abg_python/tests/test_smooth_utils.py
abg_python/tests/test_system_utils.py
abg_python-1.1.5.dist-info/LICENSE
abg_python-1.1.5.dist-info/METADATA
abg_python-1.1.5.dist-info/WHEEL
abg_python-1.1.5.dist-info/top_level.txt
abg_python-1.1.5.dist-info/RECORD
