Metadata-Version: 2.1
Name: abg-python
Version: 1.1.5
Summary: shared python utilities for http://github.com/agurvich 's packages.
Home-page: https://github.com/agurvich/abg_python
Author: Alex Gurvich
Author-email: agurvich@u.northwestern.edu
Project-URL: Bug Tracker, https://github.com/agurvich/abg_python/issues
Classifier: Programming Language :: Python :: 3
Classifier: License :: OSI Approved :: MIT License
Classifier: Operating System :: OS Independent
Requires-Python: >=3.6
License-File: LICENSE
Requires-Dist: scipy
Requires-Dist: numpy
Requires-Dist: h5py
Requires-Dist: pandas
Requires-Dist: matplotlib (>=3.5)
